{"cameraMode":{"drawMode":0,"name":"Shaded","section":"Shading Mode"},"sceneLighting":true,"audioPlay":false,"sceneViewState":{"showFog":true,"showMaterialUpdate":false,"showSkybox":true,"showFlares":true,"showImageEffects":true,"showParticleSystems":true},"in2DMode":false,"pivot":{"x":-1.7748353481292725,"y":-0.6229941844940186,"z":7.504900932312012},"rotation":{"x":0.0012385462177917362,"y":-0.9984944462776184,"z":-0.025467103347182275,"w":-0.04856695979833603},"size":10.717958450317383,"orthographic":false}